odoo8_addon_hr_employee_age-8.0.1.0.0.99.dev13-py2.7-nspkg.pth
odoo8_addon_hr_employee_age-8.0.1.0.0.99.dev13.dist-info/METADATA
odoo8_addon_hr_employee_age-8.0.1.0.0.99.dev13.dist-info/RECORD
odoo8_addon_hr_employee_age-8.0.1.0.0.99.dev13.dist-info/WHEEL
odoo8_addon_hr_employee_age-8.0.1.0.0.99.dev13.dist-info/namespace_packages.txt
odoo8_addon_hr_employee_age-8.0.1.0.0.99.dev13.dist-info/top_level.txt
odoo_addons/hr_employee_age/README.rst
odoo_addons/hr_employee_age/__init__.py
odoo_addons/hr_employee_age/__openerp__.py
odoo_addons/hr_employee_age/i18n/ar.po
odoo_addons/hr_employee_age/i18n/de.po
odoo_addons/hr_employee_age/i18n/es.po
odoo_addons/hr_employee_age/i18n/fi.po
odoo_addons/hr_employee_age/i18n/fr.po
odoo_addons/hr_employee_age/i18n/hr_employee_age.pot
odoo_addons/hr_employee_age/i18n/it.po
odoo_addons/hr_employee_age/i18n/nl.po
odoo_addons/hr_employee_age/i18n/nl_NL.po
odoo_addons/hr_employee_age/i18n/pt_BR.po
odoo_addons/hr_employee_age/i18n/ro.po
odoo_addons/hr_employee_age/i18n/sl.po
odoo_addons/hr_employee_age/models/__init__.py
odoo_addons/hr_employee_age/models/hr_employee.py
odoo_addons/hr_employee_age/static/description/icon.png
odoo_addons/hr_employee_age/views/hr_employee.xml
